<?xml version="1.0" encoding="utf-8" ?><dwsync><file name="bootstrap-colorpicker.js" server="23.23.80.150//squaretortilla/" local="3431792874" remote="12034165292" /><file name="bootstrap-datepicker.js" server="23.23.80.150//squaretortilla/" local="3431789980" remote="12034165292" /><file name="bootstrap.js" server="23.23.80.150//squaretortilla/" local="3435260450" remote="12034165292" /><file name="bootstrap.min.js" server="23.23.80.150//squaretortilla/" local="3435260448" remote="12034165292" /><file name="excanvas.js" server="23.23.80.150//squaretortilla/" local="3383663412" remote="12034165292" /><file name="excanvas.min.js" server="23.23.80.150//squaretortilla/" local="3383663412" remote="12034165292" /><file name="fullcalendar.js" server="23.23.80.150//squaretortilla/" local="3411435238" remote="12034165292" /><file name="fullcalendar.min.js" server="23.23.80.150//squaretortilla/" local="3427686288" remote="12034165292" /><file name="jquery.dataTables.js" server="23.23.80.150//squaretortilla/" local="3423219676" remote="12034165292" /><file name="jquery.dataTables.min.js" server="23.23.80.150//squaretortilla/" local="3423219684" remote="12034165292" /><file name="jquery.flot.js" server="23.23.80.150//squaretortilla/" local="3383663412" remote="12034165292" /><file name="jquery.flot.min.js" server="23.23.80.150//squaretortilla/" local="3418667058" remote="12034165292" /><file name="jquery.flot.pie.js" server="23.23.80.150//squaretortilla/" local="3419580262" remote="12034165292" /><file name="jquery.flot.pie.min.js" server="23.23.80.150//squaretortilla/" local="3383663412" remote="12034165292" /><file name="jquery.flot.resize.js" server="23.23.80.150//squaretortilla/" local="3383663412" remote="12034165292" /><file name="jquery.flot.resize.min.js" server="23.23.80.150//squaretortilla/" local="3418667060" remote="12034165292" /><file name="jquery.gritter.js" server="23.23.80.150//squaretortilla/" local="3421678966" remote="12034165292" /><file name="jquery.gritter.min.js" server="23.23.80.150//squaretortilla/" local="3421678966" remote="12034165292" /><file name="jquery.js" server="23.23.80.150//squaretortilla/" local="3425433718" remote="12034165292" /><file name="jquery.min.js" server="23.23.80.150//squaretortilla/" local="3425191086" remote="12034165292" /><file name="jquery.peity.js" server="23.23.80.150//squaretortilla/" local="3427604340" remote="12034165292" /><file name="jquery.peity.min.js" server="23.23.80.150//squaretortilla/" local="3427604376" remote="12034165292" /><file name="jquery.ui.custom.js" server="23.23.80.150//squaretortilla/" local="3425580890" remote="12034165292" /><file name="jquery.uniform.js" server="23.23.80.150//squaretortilla/" local="3414058502" remote="12034165292" /><file name="jquery.validate.js" server="23.23.80.150//squaretortilla/" local="3400784498" remote="12034165292" /><file name="jquery.wizard.js" server="23.23.80.150//squaretortilla/" local="3428433186" remote="12034165292" /><file name="select2.js" server="23.23.80.150//squaretortilla/" local="3435164000" remote="12034165292" /><file name="select2.min.js" server="23.23.80.150//squaretortilla/" local="3435164000" remote="12034165292" /><file name="unicorn.calendar.js" server="23.23.80.150//squaretortilla/" local="3432182584" remote="12034165292" /><file name="unicorn.charts.js" server="23.23.80.150//squaretortilla/" local="3432182592" remote="12034165292" /><file name="unicorn.chat.js" server="23.23.80.150//squaretortilla/" local="3432182598" remote="12034165292" /><file name="unicorn.dashboard.js" server="23.23.80.150//squaretortilla/" local="3432182604" remote="12034165292" /><file name="unicorn.form_common.js" server="23.23.80.150//squaretortilla/" local="3435164170" remote="12034165292" /><file name="unicorn.form_validation.js" server="23.23.80.150//squaretortilla/" local="3435283912" remote="12034165292" /><file name="unicorn.interface.js" server="23.23.80.150//squaretortilla/" local="3432182634" remote="12034165292" /><file name="unicorn.js" server="23.23.80.150//squaretortilla/" local="3432182640" remote="12034165292" /><file name="unicorn.login.js" server="23.23.80.150//squaretortilla/" local="3432182648" remote="12034165292" /><file name="unicorn.tables.js" server="23.23.80.150//squaretortilla/" local="3435260774" remote="12034165352" /><file name="unicorn.wizard.js" server="23.23.80.150//squaretortilla/" local="3432182660" remote="12034165352" /></dwsync>